mcss_package/__init__.py
mcss_package/alignment.py
mcss_package/clustering.py
mcss_package/config.py
mcss_package/runner.py
mcss_package-0.1.0.dist-info/licenses/LICENSE
mcss_package-0.1.0.dist-info/METADATA
mcss_package-0.1.0.dist-info/WHEEL
mcss_package-0.1.0.dist-info/top_level.txt
mcss_package-0.1.0.dist-info/RECORD
